{
	"configurations" : 
	[
		{
			"directories" : 
			[
				{
					"build" : ".",
					"jsonFile" : "directory-.-Debug-f5ebdc15457944623624.json",
					"minimumCMakeVersion" : 
					{
						"string" : "3.22"
					},
					"projectIndex" : 0,
					"source" : ".",
					"targetIndexes" : 
					[
						0
					]
				}
			],
			"name" : "Debug",
			"projects" : 
			[
				{
					"directoryIndexes" : 
					[
						0
					],
					"name" : "CppCourse",
					"targetIndexes" : 
					[
						0
					]
				}
			],
			"targets" : 
			[
				{
					"directoryIndex" : 0,
					"id" : "CppCourse::@6890427a1f51a3e7e1df",
					"jsonFile" : "target-CppCourse-Debug-3b823dfa940e61c35624.json",
					"name" : "CppCourse",
					"projectIndex" : 0
				}
			]
		}
	],
	"kind" : "codemodel",
	"paths" : 
	{
		"build" : "/cygdrive/c/Users/nimrod/Documents/GitHub/CppCourse/cmake-build-debug",
		"source" : "/cygdrive/c/Users/nimrod/Documents/GitHub/CppCourse"
	},
	"version" : 
	{
		"major" : 2,
		"minor" : 3
	}
}
